MANIFEST.in
README.txt
requirements.txt
setup.py
test_requirements.txt
version.txt
cloudshell/__init__.py
cloudshell/power/__init__.py
cloudshell/power/pdu/__init__.py
cloudshell/power/pdu/mibs/INET-ADDRESS-MIB.py
cloudshell/power/pdu/mibs/PDU2-MIB.py
cloudshell/power/pdu/mibs/SNMPv2-MIB.py
cloudshell/power/pdu/mibs/__init__.py
cloudshell/power/pdu/raritan/__init__.py
cloudshell/power/pdu/raritan/raritan_handler.py
cloudshell/power/pdu/raritan/raritan_resource_driver.py
cloudshell/power/pdu/raritan/shell_helper.py
cloudshell/power/pdu/raritan/device/__init__.py
cloudshell/power/pdu/raritan/device/factory_context.py
cloudshell/power/pdu/raritan/device/raritan_rpcapi_pdu_factory.py
cloudshell/power/pdu/raritan/device/rpcapi_outlet.py
cloudshell_pdu_raritan.egg-info/PKG-INFO
cloudshell_pdu_raritan.egg-info/SOURCES.txt
cloudshell_pdu_raritan.egg-info/dependency_links.txt
cloudshell_pdu_raritan.egg-info/requires.txt
cloudshell_pdu_raritan.egg-info/top_level.txt
raritan/__init__.py
raritan/rpc/Agent.py
raritan/rpc/Enumeration.py
raritan/rpc/Interface.py
raritan/rpc/Structure.py
raritan/rpc/Time.py
raritan/rpc/TypeInfo.py
raritan/rpc/Utils.py
raritan/rpc/ValueObject.py
raritan/rpc/__init__.py
raritan/rpc/typecheck.py
raritan/rpc/assetmgrmodel/__init__.py
raritan/rpc/auth/__init__.py
raritan/rpc/auth/ldapsrv/__init__.py
raritan/rpc/bulkcfg/__init__.py
raritan/rpc/bulkrpc/__init__.py
raritan/rpc/cascading/__init__.py
raritan/rpc/cert/__init__.py
raritan/rpc/cew/__init__.py
raritan/rpc/cfg/__init__.py
raritan/rpc/datetime/__init__.py
raritan/rpc/devsettings/__init__.py
raritan/rpc/diag/__init__.py
raritan/rpc/display/__init__.py
raritan/rpc/emdmodel/__init__.py
raritan/rpc/event/__init__.py
raritan/rpc/firmware/__init__.py
raritan/rpc/fitness/__init__.py
raritan/rpc/hmi/__init__.py
raritan/rpc/idl/__init__.py
raritan/rpc/jsonrpc/__init__.py
raritan/rpc/lhx/__init__.py
raritan/rpc/lhxmodel/__init__.py
raritan/rpc/logging/__init__.py
raritan/rpc/modbus/__init__.py
raritan/rpc/net/__init__.py
raritan/rpc/opaque/__init__.py
raritan/rpc/opaque/bulkrpc.py
raritan/rpc/pdumodel/__init__.py
raritan/rpc/peripheral/__init__.py
raritan/rpc/portsmodel/__init__.py
raritan/rpc/powerlogic/__init__.py
