Metadata-Version: 1.0
Name: cloudshell-pdu-raritan
Version: 1.0.55
Summary: QualiSystems Raritan PDU package
Home-page: http://www.qualisystems.com/
Author: QualiSystems
Author-email: info@qualisystems.com
License: UNKNOWN
Platform: UNKNOWN
